extractly/__init__.py
extractly/chunking.py
extractly/config.py
extractly/extractor.py
extractly/ocr.py
extractly/schemas.py
extractly/actions/__init__.py
extractly/actions/defaults.py
extractly/actions/orchestrator.py
extractly/actions/schemas.py
extractly/fields/__init__.py
extractly/fields/repository.py
extractly/prompts/__init__.py
extractly/prompts/defaults.py
extractly/prompts/orchestrator.py
extractly-0.4.0.dist-info/METADATA
extractly-0.4.0.dist-info/WHEEL
extractly-0.4.0.dist-info/top_level.txt
extractly-0.4.0.dist-info/RECORD
