Metadata-Version: 2.4
Name: extractly
Version: 0.4.0
Summary: Document data extraction made by Dark Matter
Author-email: Francisco Macedo <franciscovcbm@gmail.com>
Requires-Python: >=3.10
Requires-Dist: mistralai>=1.9.11
Requires-Dist: pydantic-ai>=1.0.17
Requires-Dist: python-dotenv>=1.1.1
Requires-Dist: tenacity>=9.1.2
Provides-Extra: dev
Requires-Dist: basedpyright>=1.31.7; extra == "dev"
Requires-Dist: build>=1.2.1; extra == "dev"
Requires-Dist: pre-commit>=3.7.1; extra == "dev"
Requires-Dist: pytest>=8.4.2; extra == "dev"
Requires-Dist: pytest-env>=1.1.5; extra == "dev"
Requires-Dist: ruff>=0.14.2; extra == "dev"
Requires-Dist: twine>=5.1.1; extra == "dev"
